client_connection.py
server_contracts.py
connection_builder/__init__.py
connection_builder/client_connection_builder.py
connection_builder/client_connection_builder_factory.py
connection_builder/exceptions.py
connection_builder/iclient_connection_builder.py
method_processing/__init__.py
method_processing/method_discovery.py
method_processing/method_function_handler_generator.py
method_processing/method_parsing.py
middleman_danel-1.0.4.dist-info/METADATA
middleman_danel-1.0.4.dist-info/WHEEL
middleman_danel-1.0.4.dist-info/top_level.txt
middleman_danel-1.0.4.dist-info/RECORD
