Metadata-Version: 2.4
Name: middleman-danel
Version: 1.0.4
Summary: Python client library for MiddleMan applications
Author: andyyy2k
License-Expression: MIT
Project-URL: Homepage, https://example.com/middleman-client-python
Classifier: Development Status :: 4 - Beta
Classifier: Intended Audience :: Developers
Classifier: Operating System :: OS Independent
Classifier: Programming Language :: Python :: 3
Classifier: Programming Language :: Python :: 3.8
Classifier: Programming Language :: Python :: 3.9
Classifier: Programming Language :: Python :: 3.10
Classifier: Programming Language :: Python :: 3.11
Classifier: Programming Language :: Python :: 3.12
Requires-Python: >=3.8
Requires-Dist: signalrcore>=0.9.5
Requires-Dist: websockets>=11.0
Requires-Dist: typing-extensions>=4.0.0
Requires-Dist: aiohttp>=3.8.0
Dynamic: requires-python
